fstringen/__init__.py
fstringen/generator.py
fstringen/generator_test.py
fstringen/integration_test.py
fstringen/model.py
fstringen/model_test.py
fstringen-0.0.14.dist-info/LICENSE
fstringen-0.0.14.dist-info/METADATA
fstringen-0.0.14.dist-info/WHEEL
fstringen-0.0.14.dist-info/top_level.txt
fstringen-0.0.14.dist-info/RECORD
