Metadata-Version: 2.1
Name: fstringen
Version: 0.0.14
Summary: A text generator based on f-strings
Home-page: https://github.com/alnvdl/fstringen
Author: Allan Vidal
License: UNKNOWN
Platform: UNKNOWN
Classifier: Development Status :: 4 - Beta
Classifier: Operating System :: OS Independent
Classifier: Topic :: Software Development :: Code Generators
Classifier: License :: OSI Approved :: Apache Software License
Requires-Python: >=3.6
